{"frame_second": "1700", "additional_id_existed_ped": {"0": [], "1": [88, 90, 91], "2": [89, 91], "3": [88, 89, 90, 91], "4": [88, 89, 90], "5": [90], "6": [89, 90, 91], "7": [89, 91], "8": [89, 90], "9": [91], "10": [89], "11": [88, 89, 90, 91], "12": [89], "13": [88, 90, 91], "14": [88, 90], "15": [88, 89], "16": [], "17": [88], "18": [89, 91], "19": [88, 89, 90], "20": [], "21": [90], "22": [90, 91], "23": [88, 89, 91], "24": [88, 90], "25": [88, 89, 91], "26": [88, 89, 90, 91], "27": [88, 90], "28": [88, 90, 91], "29": [88, 90, 91], "30": [90, 91], "31": [88], "32": [89], "33": [88, 89, 90, 91], "34": [88, 90, 91], "35": [89], "36": [], "37": [88, 89, 90, 91], "38": [], "39": [89], "40": [88], "41": [89, 91], "42": [88], "43": [88, 90, 91], "44": [88, 90, 91], "45": [89, 90, 91], "46": [88, 89, 90], "47": [88, 89, 90, 91], "48": [90], "49": [89, 90, 91], "50": [88], "51": [88], "52": [89, 91], "53": [88, 91], "54": [88, 89], "55": [90, 91], "56": [89, 91], "57": [90, 91], "58": [88, 89, 91], "59": [88, 89, 91], "60": [89, 91], "61": [88, 89, 90], "62": [88, 90, 91], "63": [88], "64": [88, 89, 90], "65": [88, 89, 90], "66": [91], "67": [], "68": [89, 90], "69": [89], "70": [89, 91], "71": [89, 90], "72": [91], "73": [88, 90], "74": [88], "75": [88, 89, 91], "76": [89, 90, 91], "77": [], "78": [88, 89, 90, 91], "79": [88, 90, 91], "80": [89, 91], "81": [90], "82": [88, 90], "83": [90, 91], "84": [89, 90], "85": [88], "86": [89], "87": [91]}, "pedestrian_list": [{"in_group_r_range": 2.0, "attractor_count": 44, "target": [16.0, -39.0], "out_group_a_strength": 10.0, "out_group_r_strength": 80.0, "out_group_r_range": 2.0, "in_group_a_strength": 20, "position": [4.691309705114837, 63.735943895298924], "friend_zone": [72, 22, 53, 27, 10, 7, 36, 56, 38, 87, 42, 60, 71, 59, 9, 64, 74, 32, 28, 8, 18, 82, 58, 21, 48, 20, 75, 44, 2, 23, 11, 80, 30, 16, 61, 65, 26, 62, 12, 3, 54, 55, 84, 78], "in_group_r_strength": 40, "out_group_a_range": 2.8, "pedestrian_id": 88, "target_a_strength": 22000000000, "group_id": 0, "target_a_range": 435, "radius": 0.3, "in_group_a_range": 2.8}, {"in_group_r_range": 2.0, "attractor_count": 44, "target": [16.0, -39.0], "out_group_a_strength": 10.0, "out_group_r_strength": 80.0, "out_group_r_range": 2.0, "in_group_a_strength": 20, "position": [18.959349224386674, 55.318841633051846], "friend_zone": [35, 27, 75, 37, 21, 48, 39, 85, 3, 38, 15, 41, 66, 60, 80, 13, 83, 72, 40, 33, 32, 57, 76, 67, 70, 9, 68, 34, 10, 52, 78, 28, 59, 19, 79, 69, 87, 64, 47, 26, 46, 29, 2, 25], "in_group_r_strength": 40, "out_group_a_range": 2.8, "pedestrian_id": 89, "target_a_strength": 22000000000, "group_id": 0, "target_a_range": 435, "radius": 0.3, "in_group_a_range": 2.8}, {"in_group_r_range": 2.0, "attractor_count": 44, "target": [16.0, -39.0], "out_group_a_strength": 10.0, "out_group_r_strength": 80.0, "out_group_r_range": 2.0, "in_group_a_strength": 20, "position": [2.7168360476828455, 68.96275762427372], "friend_zone": [87, 9, 52, 29, 11, 20, 79, 16, 37, 2, 26, 51, 84, 49, 0, 83, 13, 75, 74, 78, 85, 35, 32, 31, 36, 77, 41, 61, 44, 56, 43, 39, 33, 17, 23, 47, 82, 60, 28, 7, 5, 65, 24, 4], "in_group_r_strength": 40, "out_group_a_range": 2.8, "pedestrian_id": 90, "target_a_strength": 22000000000, "group_id": 1, "target_a_range": 435, "radius": 0.3, "in_group_a_range": 2.8}, {"in_group_r_range": 2.0, "attractor_count": 44, "target": [16.0, -39.0], "out_group_a_strength": 10.0, "out_group_r_strength": 80.0, "out_group_r_range": 2.0, "in_group_a_strength": 20, "position": [10.51576197443724, 71.55925034062443], "friend_zone": [50, 80, 82, 6, 7, 9, 14, 44, 40, 81, 72, 11, 41, 63, 1, 28, 34, 26, 32, 31, 74, 8, 43, 48, 16, 69, 13, 35, 71, 49, 60, 78, 3, 65, 56, 75, 19, 67, 24, 87, 46, 38, 66, 47], "in_group_r_strength": 40, "out_group_a_range": 2.8, "pedestrian_id": 91, "target_a_strength": 22000000000, "group_id": 1, "target_a_range": 435, "radius": 0.3, "in_group_a_range": 2.8}]}