{"additional_id_existed_ped": [], "frame_second": 2000, "pedestrian_list": [{"out_group_a_strength": 11.764705882352942, "friend_zone": [6, 18, 15, 2, 7, 19, 8, 10, 16, 5, 20, 22, 24, 26, 27, 28, 29, 31, 34, 35, 40, 41, 42, 44, 46, 47, 48, 49, 51, 53, 56, 60, 61, 63, 66, 70, 71, 74, 77, 78, 82, 83, 86, 87, 88, 90, 93, 94, 96, 97], "out_group_r_range": 2.0, "target_a_strength": 22000000000.0, "radius": 0.3, "out_group_a_range": 2.8, "pedestrian_id": 0, "target_a_range": 435.0, "in_group_r_range": 2.0, "target": [10000.0, 0.0], "in_group_a_range": 2.8, "out_group_r_strength": 68.0, "attractor_count": 50, "in_group_r_strength": 40.0, "in_group_a_strength": 20.0, "position": [52.788805094101285, -8.035932026099587], "group_id": 0.0}, {"out_group_a_strength": 11.764705882352942, "friend_zone": [2, 3, 19, 8, 11, 10, 6, 17, 9, 18, 20, 27, 30, 31, 37, 38, 40, 41, 42, 43, 48, 49, 54, 55, 56, 57, 59, 60, 62, 64, 67, 68, 69, 70, 72, 76, 80, 83, 84, 87, 91, 92, 94, 95, 96, 98], "out_group_r_range": 2.0, "target_a_strength": 22000000000.0, "radius": 0.3, "out_group_a_range": 2.8, "pedestrian_id": 1, "target_a_range": 435.0, "in_group_r_range": 2.0, "target": [10000.0, 0.0], "in_group_a_range": 2.8, "out_group_r_strength": 68.0, "attractor_count": 46, "in_group_r_strength": 40.0, "in_group_a_strength": 20.0, "position": [27.75938391338277, -0.19327449899803337], "group_id": 0.0}, {"out_group_a_strength": 11.764705882352942, "friend_zone": [6, 5, 7, 10, 13, 19, 3, 14, 15, 12, 23, 27, 28, 29, 32, 33, 34, 41, 43, 44, 45, 46, 47, 49, 50, 51, 53, 54, 55, 56, 57, 59, 60, 62, 63, 64, 65, 66, 68, 70, 74, 76, 77, 79, 83, 85, 88, 95, 96, 97, 99], "out_group_r_range": 2.0, "target_a_strength": 22000000000.0, "radius": 0.3, "out_group_a_range": 2.8, "pedestrian_id": 2, "target_a_range": 435.0, "in_group_r_range": 2.0, "target": [10000.0, 0.0], "in_group_a_range": 2.8, "out_group_r_strength": 68.0, "attractor_count": 51, "in_group_r_strength": 40.0, "in_group_a_strength": 20.0, "position": [17.59978561672765, 5.873220086776271], "group_id": 0.0}, {"out_group_a_strength": 11.764705882352942, "friend_zone": [18, 10, 12, 0, 5, 9, 6, 13, 16, 14, 22, 26, 27, 29, 31, 33, 34, 36, 37, 38, 39, 41, 42, 43, 44, 46, 47, 50, 52, 53, 54, 55, 61, 62, 64, 65, 67, 69, 70, 72, 75, 76, 77, 80, 82, 84, 85, 88, 90, 92, 95, 96, 97], "out_group_r_range": 2.0, "target_a_strength": 22000000000.0, "radius": 0.3, "out_group_a_range": 2.8, "pedestrian_id": 3, "target_a_range": 435.0, "in_group_r_range": 2.0, "target": [10000.0, 0.0], "in_group_a_range": 2.8, "out_group_r_strength": 68.0, "attractor_count": 53, "in_group_r_strength": 40.0, "in_group_a_strength": 20.0, "position": [81.22055035901322, -1.4548693139474822], "group_id": 0.0}, {"out_group_a_strength": 11.764705882352942, "friend_zone": [15, 7, 8, 5, 1, 11, 3, 19, 16, 9, 21, 24, 25, 26, 27, 28, 29, 31, 33, 34, 36, 37, 41, 44, 45, 47, 48, 49, 50, 51, 54, 58, 59, 62, 64, 67, 69, 70, 71, 79, 80, 81, 82, 83, 85, 89, 91, 94, 95, 96, 98, 99], "out_group_r_range": 2.0, "target_a_strength": 22000000000.0, "radius": 0.3, "out_group_a_range": 2.8, "pedestrian_id": 4, "target_a_range": 435.0, "in_group_r_range": 2.0, "target": [10000.0, 0.0], "in_group_a_range": 2.8, "out_group_r_strength": 68.0, "attractor_count": 52, "in_group_r_strength": 40.0, "in_group_a_strength": 20.0, "position": [63.301135372573206, -4.654682881691024], "group_id": 0.0}, {"out_group_a_strength": 11.764705882352942, "friend_zone": [1, 2, 17, 14, 3, 9, 7, 15, 19, 18, 20, 22, 23, 25, 26, 29, 30, 32, 33, 34, 35, 38, 39, 40, 43, 44, 45, 46, 47, 51, 52, 53, 54, 57, 59, 61, 64, 66, 68, 71, 77, 80, 82, 83, 84, 85, 89, 90, 93, 96, 97], "out_group_r_range": 2.0, "target_a_strength": 22000000000.0, "radius": 0.3, "out_group_a_range": 2.8, "pedestrian_id": 5, "target_a_range": 435.0, "in_group_r_range": 2.0, "target": [10000.0, 0.0], "in_group_a_range": 2.8, "out_group_r_strength": 68.0, "attractor_count": 51, "in_group_r_strength": 40.0, "in_group_a_strength": 20.0, "position": [73.27651589442958, 2.6300468610895718], "group_id": 0.0}, {"out_group_a_strength": 11.764705882352942, "friend_zone": [1, 14, 16, 12, 7, 15, 18, 13, 17, 19, 21, 23, 24, 27, 29, 37, 38, 39, 42, 44, 46, 48, 50, 51, 52, 55, 59, 69, 70, 72, 73, 74, 75, 77, 80, 81, 82, 83, 85, 89, 91, 93, 94], "out_group_r_range": 2.0, "target_a_strength": 22000000000.0, "radius": 0.3, "out_group_a_range": 2.8, "pedestrian_id": 6, "target_a_range": 435.0, "in_group_r_range": 2.0, "target": [10000.0, 0.0], "in_group_a_range": 2.8, "out_group_r_strength": 68.0, "attractor_count": 43, "in_group_r_strength": 40.0, "in_group_a_strength": 20.0, "position": [61.45046625929619, 1.6969243083963073], "group_id": 0.0}, {"out_group_a_strength": 11.764705882352942, "friend_zone": [6, 15, 4, 10, 11, 8, 13, 19, 1, 12, 21, 24, 25, 28, 30, 31, 33, 34, 37, 38, 39, 45, 46, 47, 48, 50, 51, 53, 55, 57, 59, 62, 66, 68, 71, 74, 76, 78, 79, 80, 84, 86, 87, 90, 92, 93, 94, 96, 97, 98], "out_group_r_range": 2.0, "target_a_strength": 22000000000.0, "radius": 0.3, "out_group_a_range": 2.8, "pedestrian_id": 7, "target_a_range": 435.0, "in_group_r_range": 2.0, "target": [10000.0, 0.0], "in_group_a_range": 2.8, "out_group_r_strength": 68.0, "attractor_count": 50, "in_group_r_strength": 40.0, "in_group_a_strength": 20.0, "position": [65.5068919901021, -7.104632182690344], "group_id": 0.0}, {"out_group_a_strength": 11.764705882352942, "friend_zone": [13, 4, 6, 17, 19, 5, 10, 15, 18, 7, 21, 24, 34, 35, 37, 38, 40, 41, 42, 43, 44, 49, 50, 52, 55, 56, 57, 58, 60, 62, 63, 64, 65, 66, 67, 68, 70, 71, 72, 76, 77, 81, 82, 84, 85, 87, 89, 90, 94, 98, 99], "out_group_r_range": 2.0, "target_a_strength": 22000000000.0, "radius": 0.3, "out_group_a_range": 2.8, "pedestrian_id": 8, "target_a_range": 435.0, "in_group_r_range": 2.0, "target": [10000.0, 0.0], "in_group_a_range": 2.8, "out_group_r_strength": 68.0, "attractor_count": 51, "in_group_r_strength": 40.0, "in_group_a_strength": 20.0, "position": [33.89800699901154, 8.867861374376197], "group_id": 0.0}, {"out_group_a_strength": 11.764705882352942, "friend_zone": [2, 13, 3, 19, 16, 10, 1, 5, 11, 8, 20, 22, 23, 26, 27, 28, 30, 31, 36, 40, 44, 46, 47, 48, 51, 52, 53, 54, 56, 57, 60, 63, 69, 70, 73, 75, 79, 80, 85, 86, 88, 89, 93, 95, 96, 98, 99], "out_group_r_range": 2.0, "target_a_strength": 22000000000.0, "radius": 0.3, "out_group_a_range": 2.8, "pedestrian_id": 9, "target_a_range": 435.0, "in_group_r_range": 2.0, "target": [10000.0, 0.0], "in_group_a_range": 2.8, "out_group_r_strength": 68.0, "attractor_count": 47, "in_group_r_strength": 40.0, "in_group_a_strength": 20.0, "position": [84.77095806295215, -1.646321869465866], "group_id": 0.0}, {"out_group_a_strength": 11.764705882352942, "friend_zone": [19, 2, 7, 18, 3, 5, 10, 13, 9, 16, 24, 28, 29, 30, 31, 32, 36, 38, 39, 40, 42, 43, 48, 52, 53, 54, 55, 57, 59, 60, 61, 62, 63, 65, 66, 71, 73, 74, 75, 76, 79, 80, 84, 87, 89, 90, 91, 94], "out_group_r_range": 2.0, "target_a_strength": 22000000000.0, "radius": 0.3, "out_group_a_range": 2.8, "pedestrian_id": 20, "target_a_range": 435.0, "in_group_r_range": 2.0, "target": [10000.0, 0.0], "in_group_a_range": 2.8, "out_group_r_strength": 68.0, "attractor_count": 48, "in_group_r_strength": 40.0, "in_group_a_strength": 20.0, "position": [76.24624140301034, 2.9415071562307906], "group_id": 0.0}, {"out_group_a_strength": 11.764705882352942, "friend_zone": [19, 17, 8, 4, 3, 12, 5, 1, 2, 9, 24, 26, 28, 29, 30, 33, 34, 36, 37, 38, 44, 45, 47, 48, 50, 53, 55, 57, 58, 59, 60, 62, 63, 64, 65, 67, 68, 72, 73, 76, 81, 83, 85, 86, 88, 89, 91, 94, 95, 97, 98, 99], "out_group_r_range": 2.0, "target_a_strength": 22000000000.0, "radius": 0.3, "out_group_a_range": 2.8, "pedestrian_id": 21, "target_a_range": 435.0, "in_group_r_range": 2.0, "target": [10000.0, 0.0], "in_group_a_range": 2.8, "out_group_r_strength": 68.0, "attractor_count": 52, "in_group_r_strength": 40.0, "in_group_a_strength": 20.0, "position": [76.32698850772036, -2.8932163675127303], "group_id": 0.0}, {"out_group_a_strength": 11.764705882352942, "friend_zone": [7, 22, 18, 23, 3, 14, 21, 8, 2, 20, 4, 15, 28, 30, 32, 35, 38, 41, 42, 44, 45, 46, 47, 51, 54, 55, 56, 57, 60, 61, 63, 65, 66, 68, 69, 70, 71, 72, 74, 75, 78, 79, 81, 82, 84, 86, 87, 90, 96, 97], "out_group_r_range": 2.0, "target_a_strength": 22000000000.0, "radius": 0.3, "out_group_a_range": 2.8, "pedestrian_id": 24, "target_a_range": 435.0, "in_group_r_range": 2.0, "target": [10000.0, 0.0], "in_group_a_range": 2.8, "out_group_r_strength": 68.0, "attractor_count": 50, "in_group_r_strength": 40.0, "in_group_a_strength": 20.0, "position": [102.28144371978327, 0.09227270770378643], "group_id": 0.0}, {"out_group_a_strength": 11.764705882352942, "friend_zone": [1, 12, 2, 22, 20, 13, 6, 4, 15, 5, 21, 17, 29, 30, 31, 32, 37, 40, 43, 48, 49, 51, 54, 55, 57, 58, 59, 61, 62, 63, 71, 72, 76, 82, 83, 84, 86, 88, 89, 91, 92, 95], "out_group_r_range": 2.0, "target_a_strength": 22000000000.0, "radius": 0.3, "out_group_a_range": 2.8, "pedestrian_id": 25, "target_a_range": 435.0, "in_group_r_range": 2.0, "target": [10000.0, 0.0], "in_group_a_range": 2.8, "out_group_r_strength": 68.0, "attractor_count": 42, "in_group_r_strength": 40.0, "in_group_a_strength": 20.0, "position": [59.112104694428744, 6.611426600558166], "group_id": 0.0}, {"out_group_a_strength": 11.764705882352942, "friend_zone": [7, 14, 24, 3, 15, 21, 27, 17, 8, 2, 9, 1, 6, 0, 32, 35, 42, 43, 45, 53, 54, 55, 56, 58, 60, 62, 63, 64, 66, 68, 69, 73, 74, 75, 76, 77, 78, 81, 82, 84, 86, 90, 92, 93, 96, 98], "out_group_r_range": 2.0, "target_a_strength": 22000000000.0, "radius": 0.3, "out_group_a_range": 2.8, "pedestrian_id": 28, "target_a_range": 435.0, "in_group_r_range": 2.0, "target": [10000.0, 0.0], "in_group_a_range": 2.8, "out_group_r_strength": 68.0, "attractor_count": 46, "in_group_r_strength": 40.0, "in_group_a_strength": 20.0, "position": [71.77519488122378, -2.391280706533025], "group_id": 0.0}, {"out_group_a_strength": 11.764705882352942, "friend_zone": [20, 19, 8, 3, 22, 17, 6, 11, 24, 15, 2, 13, 9, 0, 33, 35, 37, 38, 39, 40, 45, 48, 49, 50, 51, 52, 53, 59, 60, 61, 65, 66, 67, 70, 72, 73, 74, 76, 77, 79, 80, 81, 82, 88, 89, 93, 95, 96, 97], "out_group_r_range": 2.0, "target_a_strength": 22000000000.0, "radius": 0.3, "out_group_a_range": 2.8, "pedestrian_id": 29, "target_a_range": 435.0, "in_group_r_range": 2.0, "target": [10000.0, 0.0], "in_group_a_range": 2.8, "out_group_r_strength": 68.0, "attractor_count": 49, "in_group_r_strength": 40.0, "in_group_a_strength": 20.0, "position": [63.477047665126435, 6.95174926528435], "group_id": 0.0}, {"out_group_a_strength": 11.764705882352942, "friend_zone": [30, 22, 24, 28, 18, 10, 9, 29, 6, 11, 16, 8, 3, 31, 7, 17, 36, 37, 39, 40, 41, 42, 44, 48, 53, 54, 55, 59, 60, 61, 62, 65, 66, 67, 69, 70, 71, 72, 73, 74, 80, 82, 85, 89, 90, 91, 93, 95, 97, 98, 99], "out_group_r_range": 2.0, "target_a_strength": 22000000000.0, "radius": 0.3, "out_group_a_range": 2.8, "pedestrian_id": 32, "target_a_range": 435.0, "in_group_r_range": 2.0, "target": [10000.0, 0.0], "in_group_a_range": 2.8, "out_group_r_strength": 68.0, "attractor_count": 51, "in_group_r_strength": 40.0, "in_group_a_strength": 20.0, "position": [69.4538890038226, 0.47550647908266436], "group_id": 0.0}, {"out_group_a_strength": 11.764705882352942, "friend_zone": [22, 6, 31, 3, 16, 8, 10, 11, 7, 1, 25, 30, 21, 29, 15, 17, 36, 37, 38, 39, 42, 44, 45, 46, 47, 51, 53, 54, 55, 57, 62, 66, 67, 72, 73, 75, 78, 82, 83, 84, 86, 87, 88, 92, 94, 95, 97], "out_group_r_range": 2.0, "target_a_strength": 22000000000.0, "radius": 0.3, "out_group_a_range": 2.8, "pedestrian_id": 33, "target_a_range": 435.0, "in_group_r_range": 2.0, "target": [10000.0, 0.0], "in_group_a_range": 2.8, "out_group_r_strength": 68.0, "attractor_count": 47, "in_group_r_strength": 40.0, "in_group_a_strength": 20.0, "position": [33.06676097475495, -2.678889589867744], "group_id": 0.0}, {"out_group_a_strength": 11.764705882352942, "friend_zone": [19, 29, 4, 10, 16, 34, 5, 32, 24, 18, 26, 2, 14, 35, 3, 27, 11, 13, 40, 41, 43, 45, 48, 50, 51, 52, 53, 56, 62, 65, 66, 68, 69, 72, 73, 74, 78, 80, 81, 82, 83, 84, 86, 87, 89, 90, 92, 93], "out_group_r_range": 2.0, "target_a_strength": 22000000000.0, "radius": 0.3, "out_group_a_range": 2.8, "pedestrian_id": 36, "target_a_range": 435.0, "in_group_r_range": 2.0, "target": [10000.0, 0.0], "in_group_a_range": 2.8, "out_group_r_strength": 68.0, "attractor_count": 48, "in_group_r_strength": 40.0, "in_group_a_strength": 20.0, "position": [40.148940309100375, 3.5783840484350673], "group_id": 0.0}, {"out_group_a_strength": 11.764705882352942, "friend_zone": [34, 3, 4, 19, 0, 5, 11, 27, 24, 21, 29, 20, 16, 25, 22, 28, 33, 15, 42, 43, 44, 45, 46, 48, 49, 52, 55, 56, 57, 58, 59, 61, 62, 64, 66, 67, 68, 70, 72, 75, 76, 79, 81, 85, 87, 90, 92, 94, 95, 97], "out_group_r_range": 2.0, "target_a_strength": 22000000000.0, "radius": 0.3, "out_group_a_range": 2.8, "pedestrian_id": 37, "target_a_range": 435.0, "in_group_r_range": 2.0, "target": [10000.0, 0.0], "in_group_a_range": 2.8, "out_group_r_strength": 68.0, "attractor_count": 50, "in_group_r_strength": 40.0, "in_group_a_strength": 20.0, "position": [11.366159033691508, -5.326231596633511], "group_id": 0.0}, {"out_group_a_strength": 11.764705882352942, "friend_zone": [6, 5, 4, 24, 30, 7, 13, 2, 32, 3, 36, 9, 19, 0, 21, 10, 39, 34, 31, 35, 46, 47, 52, 53, 56, 59, 64, 66, 68, 72, 76, 77, 78, 79, 81, 84, 85, 86, 87, 89, 90, 91], "out_group_r_range": 2.0, "target_a_strength": 22000000000.0, "radius": 0.3, "out_group_a_range": 2.8, "pedestrian_id": 40, "target_a_range": 435.0, "in_group_r_range": 2.0, "target": [10000.0, 0.0], "in_group_a_range": 2.8, "out_group_r_strength": 68.0, "attractor_count": 42, "in_group_r_strength": 40.0, "in_group_a_strength": 20.0, "position": [-0.5943879479367628, 10.970047496931942], "group_id": 0.0}, {"out_group_a_strength": 11.764705882352942, "friend_zone": [11, 12, 14, 17, 36, 10, 27, 34, 15, 7, 31, 33, 6, 26, 38, 39, 25, 21, 2, 35, 44, 45, 47, 48, 53, 54, 57, 60, 62, 65, 66, 69, 72, 74, 79, 81, 83, 86, 89, 91, 94, 95, 97, 98, 99], "out_group_r_range": 2.0, "target_a_strength": 22000000000.0, "radius": 0.3, "out_group_a_range": 2.8, "pedestrian_id": 41, "target_a_range": 435.0, "in_group_r_range": 2.0, "target": [10000.0, 0.0], "in_group_a_range": 2.8, "out_group_r_strength": 68.0, "attractor_count": 45, "in_group_r_strength": 40.0, "in_group_a_strength": 20.0, "position": [46.25663196522937, -5.773700233178302], "group_id": 0.0}, {"out_group_a_strength": 11.764705882352942, "friend_zone": [34, 4, 8, 39, 43, 19, 23, 5, 36, 40, 35, 17, 25, 24, 2, 16, 9, 14, 12, 41, 30, 1, 49, 51, 53, 56, 57, 58, 60, 61, 63, 64, 66, 69, 70, 74, 75, 78, 80, 81, 83, 84, 85, 86, 87, 88, 90, 92, 93, 94, 95, 97, 98], "out_group_r_range": 2.0, "target_a_strength": 22000000000.0, "radius": 0.3, "out_group_a_range": 2.8, "pedestrian_id": 44, "target_a_range": 435.0, "in_group_r_range": 2.0, "target": [10000.0, 0.0], "in_group_a_range": 2.8, "out_group_r_strength": 68.0, "attractor_count": 53, "in_group_r_strength": 40.0, "in_group_a_strength": 20.0, "position": [42.211181709272175, -3.2718821191395286], "group_id": 0.0}, {"out_group_a_strength": 11.764705882352942, "friend_zone": [6, 8, 1, 12, 40, 36, 32, 25, 41, 5, 22, 26, 33, 3, 7, 21, 9, 0, 11, 13, 42, 35, 52, 57, 58, 60, 61, 63, 67, 68, 72, 73, 75, 77, 78, 79, 80, 84, 86, 93, 94, 95, 96, 98, 99], "out_group_r_range": 2.0, "target_a_strength": 22000000000.0, "radius": 0.3, "out_group_a_range": 2.8, "pedestrian_id": 45, "target_a_range": 435.0, "in_group_r_range": 2.0, "target": [10000.0, 0.0], "in_group_a_range": 2.8, "out_group_r_strength": 68.0, "attractor_count": 45, "in_group_r_strength": 40.0, "in_group_a_strength": 20.0, "position": [12.202883193366747, 9.664562359087437], "group_id": 0.0}, {"out_group_a_strength": 11.764705882352942, "friend_zone": [25, 37, 28, 40, 35, 4, 19, 33, 42, 30, 18, 34, 8, 27, 23, 36, 15, 39, 41, 7, 5, 0, 10, 32, 59, 63, 64, 68, 69, 72, 73, 74, 76, 82, 89, 92, 93, 96, 98], "out_group_r_range": 2.0, "target_a_strength": 22000000000.0, "radius": 0.3, "out_group_a_range": 2.8, "pedestrian_id": 48, "target_a_range": 435.0, "in_group_r_range": 2.0, "target": [10000.0, 0.0], "in_group_a_range": 2.8, "out_group_r_strength": 68.0, "attractor_count": 39, "in_group_r_strength": 40.0, "in_group_a_strength": 20.0, "position": [30.10500432246048, 5.37144858817274], "group_id": 0.0}, {"out_group_a_strength": 11.764705882352942, "friend_zone": [13, 8, 32, 22, 36, 47, 18, 19, 39, 12, 26, 6, 34, 20, 23, 27, 2, 45, 28, 43, 30, 29, 35, 17, 58, 59, 60, 61, 62, 67, 68, 70, 71, 72, 73, 75, 78, 79, 84, 85, 86, 88, 89, 90, 92, 93, 97, 98], "out_group_r_range": 2.0, "target_a_strength": 22000000000.0, "radius": 0.3, "out_group_a_range": 2.8, "pedestrian_id": 49, "target_a_range": 435.0, "in_group_r_range": 2.0, "target": [10000.0, 0.0], "in_group_a_range": 2.8, "out_group_r_strength": 68.0, "attractor_count": 48, "in_group_r_strength": 40.0, "in_group_a_strength": 20.0, "position": [-6.487710647183018, 2.1156966196591114], "group_id": 0.0}, {"out_group_a_strength": 11.764705882352942, "friend_zone": [3, 31, 2, 40, 12, 8, 35, 22, 50, 25, 4, 47, 49, 23, 41, 51, 42, 10, 20, 36, 7, 9, 13, 28, 11, 30, 56, 57, 58, 59, 63, 65, 67, 69, 71, 74, 75, 76, 81, 82, 83, 84, 85, 86, 87, 88, 91, 92, 93, 94, 95, 96, 99], "out_group_r_range": 2.0, "target_a_strength": 22000000000.0, "radius": 0.3, "out_group_a_range": 2.8, "pedestrian_id": 52, "target_a_range": 435.0, "in_group_r_range": 2.0, "target": [10000.0, 0.0], "in_group_a_range": 2.8, "out_group_r_strength": 68.0, "attractor_count": 53, "in_group_r_strength": 40.0, "in_group_a_strength": 20.0, "position": [16.340984085091133, -9.471531342546987], "group_id": 0.0}, {"out_group_a_strength": 11.764705882352942, "friend_zone": [33, 6, 37, 22, 4, 18, 8, 10, 13, 2, 24, 35, 25, 51, 41, 15, 45, 46, 14, 39, 28, 42, 12, 44, 1, 3, 61, 64, 65, 66, 67, 69, 70, 71, 72, 73, 74, 83, 86, 92, 95, 96, 97, 98, 99], "out_group_r_range": 2.0, "target_a_strength": 22000000000.0, "radius": 0.3, "out_group_a_range": 2.8, "pedestrian_id": 53, "target_a_range": 435.0, "in_group_r_range": 2.0, "target": [10000.0, 0.0], "in_group_a_range": 2.8, "out_group_r_strength": 68.0, "attractor_count": 45, "in_group_r_strength": 40.0, "in_group_a_strength": 20.0, "position": [19.51802931645863, 2.0822650670321723], "group_id": 0.0}, {"out_group_a_strength": 11.764705882352942, "friend_zone": [3, 47, 5, 28, 33, 53, 0, 24, 14, 46, 34, 21, 36, 40, 4, 38, 26, 37, 50, 32, 29, 7, 16, 30, 6, 48, 8, 10, 61, 62, 66, 68, 69, 71, 72, 75, 78, 80, 82, 83, 89, 90, 94, 95, 96, 97], "out_group_r_range": 2.0, "target_a_strength": 22000000000.0, "radius": 0.3, "out_group_a_range": 2.8, "pedestrian_id": 56, "target_a_range": 435.0, "in_group_r_range": 2.0, "target": [10000.0, 0.0], "in_group_a_range": 2.8, "out_group_r_strength": 68.0, "attractor_count": 46, "in_group_r_strength": 40.0, "in_group_a_strength": 20.0, "position": [6.498426531731113, -4.660712361456847], "group_id": 0.0}, {"out_group_a_strength": 11.764705882352942, "friend_zone": [13, 10, 23, 53, 21, 44, 1, 40, 17, 43, 27, 3, 30, 15, 52, 46, 18, 29, 25, 49, 55, 9, 31, 38, 48, 33, 28, 24, 61, 64, 68, 70, 71, 79, 81, 82, 84, 89, 90, 91, 92, 95, 98, 99], "out_group_r_range": 2.0, "target_a_strength": 22000000000.0, "radius": 0.3, "out_group_a_range": 2.8, "pedestrian_id": 57, "target_a_range": 435.0, "in_group_r_range": 2.0, "target": [10000.0, 0.0], "in_group_a_range": 2.8, "out_group_r_strength": 68.0, "attractor_count": 44, "in_group_r_strength": 40.0, "in_group_a_strength": 20.0, "position": [7.4044005956403725, 6.986857940641881], "group_id": 0.0}, {"out_group_a_strength": 11.764705882352942, "friend_zone": [25, 56, 54, 45, 50, 20, 6, 27, 35, 7, 48, 42, 4, 57, 38, 18, 14, 29, 28, 46, 43, 52, 37, 44, 40, 9, 19, 8, 0, 39, 67, 68, 73, 75, 77, 83, 85, 86, 87, 91, 92, 94, 96, 98, 99], "out_group_r_range": 2.0, "target_a_strength": 22000000000.0, "radius": 0.3, "out_group_a_range": 2.8, "pedestrian_id": 60, "target_a_range": 435.0, "in_group_r_range": 2.0, "target": [10000.0, 0.0], "in_group_a_range": 2.8, "out_group_r_strength": 68.0, "attractor_count": 45, "in_group_r_strength": 40.0, "in_group_a_strength": 20.0, "position": [-11.752782697076874, 1.5362368399633324], "group_id": 0.0}, {"out_group_a_strength": 11.764705882352942, "friend_zone": [36, 34, 53, 19, 25, 37, 24, 18, 12, 46, 28, 49, 45, 41, 5, 22, 44, 10, 26, 1, 48, 58, 50, 31, 47, 4, 40, 52, 35, 6, 65, 66, 67, 70, 71, 73, 74, 77, 79, 83, 85, 87, 88, 89, 90, 91, 92, 94, 98], "out_group_r_range": 2.0, "target_a_strength": 22000000000.0, "radius": 0.3, "out_group_a_range": 2.8, "pedestrian_id": 61, "target_a_range": 435.0, "in_group_r_range": 2.0, "target": [10000.0, 0.0], "in_group_a_range": 2.8, "out_group_r_strength": 68.0, "attractor_count": 49, "in_group_r_strength": 40.0, "in_group_a_strength": 20.0, "position": [14.451560472341198, -2.8878960514149865], "group_id": 0.0}, {"out_group_a_strength": 11.764705882352942, "friend_zone": [5, 17, 8, 33, 18, 59, 45, 61, 26, 12, 54, 0, 38, 13, 23, 19, 10, 52, 63, 57, 14, 37, 42, 35, 27, 25, 40, 28, 4, 15, 62, 6, 72, 73, 74, 76, 77, 80, 81, 82, 83, 84, 86, 87, 88, 91, 94, 96, 97], "out_group_r_range": 2.0, "target_a_strength": 22000000000.0, "radius": 0.3, "out_group_a_range": 2.8, "pedestrian_id": 64, "target_a_range": 435.0, "in_group_r_range": 2.0, "target": [10000.0, 0.0], "in_group_a_range": 2.8, "out_group_r_strength": 68.0, "attractor_count": 49, "in_group_r_strength": 40.0, "in_group_a_strength": 20.0, "position": [-39.25318078027927, -4.116412148416665], "group_id": 0.0}, {"out_group_a_strength": 11.764705882352942, "friend_zone": [52, 28, 0, 43, 25, 40, 29, 6, 30, 56, 18, 1, 35, 26, 17, 34, 63, 10, 32, 48, 11, 39, 42, 44, 60, 15, 49, 51, 62, 24, 38, 8, 70, 75, 78, 81, 82, 83, 85, 87, 88, 89, 96, 97, 98, 99], "out_group_r_range": 2.0, "target_a_strength": 22000000000.0, "radius": 0.3, "out_group_a_range": 2.8, "pedestrian_id": 65, "target_a_range": 435.0, "in_group_r_range": 2.0, "target": [10000.0, 0.0], "in_group_a_range": 2.8, "out_group_r_strength": 68.0, "attractor_count": 46, "in_group_r_strength": 40.0, "in_group_a_strength": 20.0, "position": [-18.462467624125793, -4.944290455154614], "group_id": 0.0}, {"out_group_a_strength": 11.764705882352942, "friend_zone": [46, 51, 15, 27, 8, 30, 19, 62, 67, 23, 56, 42, 33, 18, 59, 13, 40, 54, 21, 53, 64, 50, 14, 47, 12, 26, 36, 57, 16, 1, 45, 39, 55, 63, 74, 76, 80, 82, 84, 85, 87, 88, 89, 91, 92, 95, 96, 97], "out_group_r_range": 2.0, "target_a_strength": 22000000000.0, "radius": 0.3, "out_group_a_range": 2.8, "pedestrian_id": 68, "target_a_range": 435.0, "in_group_r_range": 2.0, "target": [10000.0, 0.0], "in_group_a_range": 2.8, "out_group_r_strength": 68.0, "attractor_count": 48, "in_group_r_strength": 40.0, "in_group_a_strength": 20.0, "position": [2.0810802187754787, -3.8668616412947205], "group_id": 0.0}, {"out_group_a_strength": 11.764705882352942, "friend_zone": [61, 50, 6, 48, 60, 53, 36, 40, 3, 22, 8, 47, 39, 18, 27, 11, 49, 66, 16, 29, 59, 33, 7, 1, 32, 56, 54, 30, 35, 21, 0, 2, 17, 67, 72, 73, 77, 78, 79, 82, 84, 85, 87, 89, 91, 92, 93, 95, 96, 97, 98], "out_group_r_range": 2.0, "target_a_strength": 22000000000.0, "radius": 0.3, "out_group_a_range": 2.8, "pedestrian_id": 69, "target_a_range": 435.0, "in_group_r_range": 2.0, "target": [10000.0, 0.0], "in_group_a_range": 2.8, "out_group_r_strength": 68.0, "attractor_count": 51, "in_group_r_strength": 40.0, "in_group_a_strength": 20.0, "position": [23.640491840662083, 0.19195974727424361], "group_id": 0.0}, {"out_group_a_strength": 11.764705882352942, "friend_zone": [25, 59, 54, 67, 8, 31, 24, 13, 53, 15, 65, 27, 51, 39, 56, 19, 2, 48, 45, 70, 35, 60, 30, 44, 50, 21, 18, 42, 57, 63, 36, 16, 20, 47, 55, 61, 76, 80, 81, 82, 89, 90, 91, 93, 94, 96, 97, 98], "out_group_r_range": 2.0, "target_a_strength": 22000000000.0, "radius": 0.3, "out_group_a_range": 2.8, "pedestrian_id": 72, "target_a_range": 435.0, "in_group_r_range": 2.0, "target": [10000.0, 0.0], "in_group_a_range": 2.8, "out_group_r_strength": 68.0, "attractor_count": 48, "in_group_r_strength": 40.0, "in_group_a_strength": 20.0, "position": [-16.99364760413572, 2.950843681947623], "group_id": 0.0}, {"out_group_a_strength": 11.764705882352942, "friend_zone": [67, 10, 15, 26, 43, 54, 31, 50, 37, 12, 23, 22, 71, 69, 52, 5, 16, 6, 9, 19, 27, 3, 38, 47, 39, 35, 20, 18, 40, 8, 70, 30, 49, 60, 55, 24, 79, 80, 81, 82, 84, 86, 88, 93, 96], "out_group_r_range": 2.0, "target_a_strength": 22000000000.0, "radius": 0.3, "out_group_a_range": 2.8, "pedestrian_id": 73, "target_a_range": 435.0, "in_group_r_range": 2.0, "target": [10000.0, 0.0], "in_group_a_range": 2.8, "out_group_r_strength": 68.0, "attractor_count": 45, "in_group_r_strength": 40.0, "in_group_a_strength": 20.0, "position": [-10.242200666307959, 4.331922126817047], "group_id": 0.0}, {"out_group_a_strength": 11.764705882352942, "friend_zone": [28, 40, 52, 49, 53, 65, 51, 37, 7, 17, 21, 67, 10, 39, 31, 9, 44, 32, 18, 27, 12, 29, 58, 15, 26, 6, 56, 46, 41, 1, 73, 74, 34, 42, 59, 13, 50, 20, 82, 83, 84, 87, 88, 91, 93, 95, 96, 97], "out_group_r_range": 2.0, "target_a_strength": 22000000000.0, "radius": 0.3, "out_group_a_range": 2.8, "pedestrian_id": 76, "target_a_range": 435.0, "in_group_r_range": 2.0, "target": [10000.0, 0.0], "in_group_a_range": 2.8, "out_group_r_strength": 68.0, "attractor_count": 48, "in_group_r_strength": 40.0, "in_group_a_strength": 20.0, "position": [-46.36220547016346, -3.763031388490087], "group_id": 0.0}, {"out_group_a_strength": 11.764705882352942, "friend_zone": [11, 72, 12, 59, 60, 27, 51, 58, 42, 49, 20, 8, 37, 48, 25, 0, 5, 16, 43, 46, 65, 35, 32, 36, 2, 45, 61, 66, 41, 56, 1, 9, 19, 74, 47, 67, 62, 31, 80, 83, 86, 87, 89, 90, 93, 94, 97, 98, 99], "out_group_r_range": 2.0, "target_a_strength": 22000000000.0, "radius": 0.3, "out_group_a_range": 2.8, "pedestrian_id": 77, "target_a_range": 435.0, "in_group_r_range": 2.0, "target": [10000.0, 0.0], "in_group_a_range": 2.8, "out_group_r_strength": 68.0, "attractor_count": 49, "in_group_r_strength": 40.0, "in_group_a_strength": 20.0, "position": [-12.113678655558326, 9.269073276671373], "group_id": 0.0}, {"out_group_a_strength": 11.764705882352942, "friend_zone": [29, 11, 64, 68, 51, 45, 40, 71, 62, 31, 43, 50, 26, 0, 79, 59, 49, 58, 35, 63, 3, 18, 46, 1, 74, 22, 13, 65, 77, 10, 16, 55, 28, 32, 24, 57, 21, 2, 34, 30, 86, 87, 88, 90, 93, 94, 95, 97, 98, 99], "out_group_r_range": 2.0, "target_a_strength": 22000000000.0, "radius": 0.3, "out_group_a_range": 2.8, "pedestrian_id": 80, "target_a_range": 435.0, "in_group_r_range": 2.0, "target": [10000.0, 0.0], "in_group_a_range": 2.8, "out_group_r_strength": 68.0, "attractor_count": 50, "in_group_r_strength": 40.0, "in_group_a_strength": 20.0, "position": [-33.70678696421077, -3.0613086793200788], "group_id": 0.0}, {"out_group_a_strength": 11.764705882352942, "friend_zone": [73, 33, 41, 54, 25, 59, 71, 65, 11, 57, 10, 26, 29, 3, 13, 23, 20, 61, 77, 79, 69, 14, 42, 27, 0, 60, 53, 22, 49, 4, 7, 17, 36, 64, 63, 47, 16, 39, 19, 21, 88, 89, 91, 92, 93, 97, 98], "out_group_r_range": 2.0, "target_a_strength": 22000000000.0, "radius": 0.3, "out_group_a_range": 2.8, "pedestrian_id": 81, "target_a_range": 435.0, "in_group_r_range": 2.0, "target": [10000.0, 0.0], "in_group_a_range": 2.8, "out_group_r_strength": 68.0, "attractor_count": 47, "in_group_r_strength": 40.0, "in_group_a_strength": 20.0, "position": [-17.706015558343534, 8.66923460219729], "group_id": 0.0}, {"out_group_a_strength": 11.764705882352942, "friend_zone": [72, 35, 34, 17, 27, 7, 28, 51, 19, 15, 1, 50, 30, 29, 83, 20, 21, 69, 26, 62, 48, 11, 22, 24, 41, 64, 12, 0, 66, 74, 54, 37, 40, 73, 55, 45, 47, 60, 33, 59, 65, 53, 88, 89, 90, 92, 94, 95, 99], "out_group_r_range": 2.0, "target_a_strength": 22000000000.0, "radius": 0.3, "out_group_a_range": 2.8, "pedestrian_id": 84, "target_a_range": 435.0, "in_group_r_range": 2.0, "target": [10000.0, 0.0], "in_group_a_range": 2.8, "out_group_r_strength": 68.0, "attractor_count": 49, "in_group_r_strength": 40.0, "in_group_a_strength": 20.0, "position": [-36.599378895920964, -8.340673553863558], "group_id": 0.0}, {"out_group_a_strength": 11.764705882352942, "friend_zone": [69, 41, 45, 62, 18, 48, 49, 21, 43, 22, 82, 3, 37, 60, 71, 81, 30, 47, 72, 46, 10, 16, 78, 14, 2, 39, 34, 40, 83, 25, 6, 75, 27, 33, 68, 42, 5, 1, 24, 38, 0, 19, 88, 89, 93, 94, 96, 99], "out_group_r_range": 2.0, "target_a_strength": 22000000000.0, "radius": 0.3, "out_group_a_range": 2.8, "pedestrian_id": 85, "target_a_range": 435.0, "in_group_r_range": 2.0, "target": [10000.0, 0.0], "in_group_a_range": 2.8, "out_group_r_strength": 68.0, "attractor_count": 48, "in_group_r_strength": 40.0, "in_group_a_strength": 20.0, "position": [-42.83468154763345, 7.866626261239933], "group_id": 0.0}, {"out_group_a_strength": 11.764705882352942, "friend_zone": [36, 54, 39, 82, 10, 79, 62, 34, 50, 51, 70, 45, 83, 66, 59, 11, 72, 18, 9, 57, 0, 3, 74, 65, 14, 35, 47, 80, 46, 13, 60, 22, 29, 42, 23, 48, 87, 38, 40, 32, 76, 16, 4, 33, 94, 95, 96, 98, 99], "out_group_r_range": 2.0, "target_a_strength": 22000000000.0, "radius": 0.3, "out_group_a_range": 2.8, "pedestrian_id": 88, "target_a_range": 435.0, "in_group_r_range": 2.0, "target": [10000.0, 0.0], "in_group_a_range": 2.8, "out_group_r_strength": 68.0, "attractor_count": 49, "in_group_r_strength": 40.0, "in_group_a_strength": 20.0, "position": [-36.655009730198074, 10.131992716532244], "group_id": 0.0}, {"out_group_a_strength": 11.764705882352942, "friend_zone": [80, 28, 32, 66, 8, 42, 51, 22, 3, 1, 57, 7, 83, 25, 34, 35, 23, 48, 18, 19, 59, 85, 40, 36, 63, 69, 50, 21, 86, 65, 72, 58, 17, 47, 87, 30, 68, 56, 13, 49, 4, 71, 64, 45, 93, 96, 99], "out_group_r_range": 2.0, "target_a_strength": 22000000000.0, "radius": 0.3, "out_group_a_range": 2.8, "pedestrian_id": 89, "target_a_range": 435.0, "in_group_r_range": 2.0, "target": [10000.0, 0.0], "in_group_a_range": 2.8, "out_group_r_strength": 68.0, "attractor_count": 47, "in_group_r_strength": 40.0, "in_group_a_strength": 20.0, "position": [-56.7310184437791, -2.9978603972801787], "group_id": 0.0}, {"out_group_a_strength": 11.764705882352942, "friend_zone": [91, 3, 55, 84, 54, 56, 28, 75, 22, 76, 19, 33, 78, 4, 10, 43, 46, 85, 52, 70, 37, 9, 88, 86, 35, 90, 42, 34, 11, 44, 72, 24, 53, 61, 82, 27, 8, 77, 83, 1, 16, 20, 49, 50, 0, 71, 98], "out_group_r_range": 2.0, "target_a_strength": 22000000000.0, "radius": 0.3, "out_group_a_range": 2.8, "pedestrian_id": 92, "target_a_range": 435.0, "in_group_r_range": 2.0, "target": [10000.0, 0.0], "in_group_a_range": 2.8, "out_group_r_strength": 68.0, "attractor_count": 47, "in_group_r_strength": 40.0, "in_group_a_strength": 20.0, "position": [-49.03954912284222, -0.5320432883859781], "group_id": 0.0}, {"out_group_a_strength": 11.764705882352942, "friend_zone": [81, 61, 14, 3, 41, 7, 35, 26, 69, 32, 15, 60, 87, 42, 79, 89, 33, 31, 49, 48, 19, 47, 13, 0, 67, 28, 46, 76, 50, 53, 40, 75, 22, 85, 9, 36, 16, 63, 30, 73, 37, 11, 55, 38, 68, 39, 98, 99], "out_group_r_range": 2.0, "target_a_strength": 22000000000.0, "radius": 0.3, "out_group_a_range": 2.8, "pedestrian_id": 93, "target_a_range": 435.0, "in_group_r_range": 2.0, "target": [10000.0, 0.0], "in_group_a_range": 2.8, "out_group_r_strength": 68.0, "attractor_count": 48, "in_group_r_strength": 40.0, "in_group_a_strength": 20.0, "position": [-39.66669674615587, 6.172579491246947], "group_id": 0.0}, {"out_group_a_strength": 11.764705882352942, "friend_zone": [39, 58, 89, 6, 16, 19, 30, 14, 13, 50, 59, 91, 71, 65, 0, 68, 43, 4, 54, 67, 55, 47, 51, 61, 94, 18, 90, 95, 79, 22, 3, 2, 74, 85, 29, 69, 56, 70, 76, 82, 84, 63, 73, 17, 26, 33, 45, 38], "out_group_r_range": 2.0, "target_a_strength": 22000000000.0, "radius": 0.3, "out_group_a_range": 2.8, "pedestrian_id": 96, "target_a_range": 435.0, "in_group_r_range": 2.0, "target": [10000.0, 0.0], "in_group_a_range": 2.8, "out_group_r_strength": 68.0, "attractor_count": 48, "in_group_r_strength": 40.0, "in_group_a_strength": 20.0, "position": [-52.91731790458087, -6.3268116587878644], "group_id": 0.0}, {"out_group_a_strength": 11.764705882352942, "friend_zone": [16, 8, 24, 49, 94, 60, 22, 4, 44, 23, 15, 72, 63, 7, 25, 20, 73, 86, 21, 74, 67, 40, 81, 93, 65, 61, 89, 83, 30, 95, 27, 46, 76, 51, 50, 92, 68, 80, 0, 79, 69, 10, 35, 39, 33, 71, 77, 70], "out_group_r_range": 2.0, "target_a_strength": 22000000000.0, "radius": 0.3, "out_group_a_range": 2.8, "pedestrian_id": 97, "target_a_range": 435.0, "in_group_r_range": 2.0, "target": [10000.0, 0.0], "in_group_a_range": 2.8, "out_group_r_strength": 68.0, "attractor_count": 48, "in_group_r_strength": 40.0, "in_group_a_strength": 20.0, "position": [-54.11187869066602, 4.406401668210395], "group_id": 0.0}, {"out_group_a_strength": 11.764705882352942, "friend_zone": [1, 8, 6, 18, 12, 9, 15, 2, 0, 5, 21, 22, 23, 25, 26, 27, 28, 29, 32, 36, 40, 41, 42, 45, 47, 51, 52, 53, 54, 56, 58, 60, 61, 62, 63, 65, 66, 67, 71, 75, 76, 77, 82, 83, 84, 87, 88, 90, 91, 93, 95, 96, 97], "out_group_r_range": 2.0, "target_a_strength": 22000000000.0, "radius": 0.3, "out_group_a_range": 2.8, "pedestrian_id": 10, "target_a_range": 435.0, "in_group_r_range": 2.0, "target": [10000.0, 0.0], "in_group_a_range": 2.8, "out_group_r_strength": 68.0, "attractor_count": 53, "in_group_r_strength": 40.0, "in_group_a_strength": 20.0, "position": [108.86846151461869, -0.00320981758729034], "group_id": 1.0}, {"out_group_a_strength": 11.764705882352942, "friend_zone": [4, 12, 1, 19, 9, 13, 0, 17, 2, 5, 20, 21, 22, 25, 29, 30, 33, 36, 37, 38, 39, 40, 41, 43, 44, 45, 47, 48, 49, 50, 52, 53, 54, 61, 62, 63, 64, 65, 67, 68, 70, 71, 72, 73, 74, 75, 77, 78, 80, 81, 87, 90, 92, 93, 96, 97, 99], "out_group_r_range": 2.0, "target_a_strength": 22000000000.0, "radius": 0.3, "out_group_a_range": 2.8, "pedestrian_id": 11, "target_a_range": 435.0, "in_group_r_range": 2.0, "target": [10000.0, 0.0], "in_group_a_range": 2.8, "out_group_r_strength": 68.0, "attractor_count": 57, "in_group_r_strength": 40.0, "in_group_a_strength": 20.0, "position": [85.44945712767088, 2.6076119858363027], "group_id": 1.0}, {"out_group_a_strength": 11.764705882352942, "friend_zone": [5, 4, 6, 7, 1, 18, 19, 14, 8, 10, 22, 23, 27, 30, 31, 34, 35, 36, 41, 44, 45, 49, 50, 54, 57, 58, 60, 61, 63, 64, 65, 66, 67, 70, 73, 76, 77, 78, 86, 91, 93, 94, 95, 96], "out_group_r_range": 2.0, "target_a_strength": 22000000000.0, "radius": 0.3, "out_group_a_range": 2.8, "pedestrian_id": 12, "target_a_range": 435.0, "in_group_r_range": 2.0, "target": [10000.0, 0.0], "in_group_a_range": 2.8, "out_group_r_strength": 68.0, "attractor_count": 44, "in_group_r_strength": 40.0, "in_group_a_strength": 20.0, "position": [73.16229100887519, -6.124635449216833], "group_id": 1.0}, {"out_group_a_strength": 11.764705882352942, "friend_zone": [5, 1, 9, 11, 14, 16, 10, 12, 15, 8, 26, 32, 33, 34, 35, 36, 38, 39, 41, 44, 45, 46, 47, 50, 52, 54, 58, 59, 61, 63, 64, 66, 68, 69, 70, 72, 73, 75, 76, 77, 79, 81, 83, 84, 86, 87, 88, 89, 91, 92, 93, 94, 96, 97, 99], "out_group_r_range": 2.0, "target_a_strength": 22000000000.0, "radius": 0.3, "out_group_a_range": 2.8, "pedestrian_id": 13, "target_a_range": 435.0, "in_group_r_range": 2.0, "target": [10000.0, 0.0], "in_group_a_range": 2.8, "out_group_r_strength": 68.0, "attractor_count": 55, "in_group_r_strength": 40.0, "in_group_a_strength": 20.0, "position": [97.40043402574706, -0.41326033144196184], "group_id": 1.0}, {"out_group_a_strength": 11.764705882352942, "friend_zone": [1, 10, 7, 18, 4, 17, 15, 5, 9, 19, 20, 21, 22, 25, 26, 29, 33, 37, 40, 42, 43, 45, 46, 47, 48, 50, 51, 53, 54, 56, 57, 58, 60, 63, 65, 69, 73, 77, 78, 80, 81, 82, 87, 88, 91, 93, 95, 97, 98], "out_group_r_range": 2.0, "target_a_strength": 22000000000.0, "radius": 0.3, "out_group_a_range": 2.8, "pedestrian_id": 14, "target_a_range": 435.0, "in_group_r_range": 2.0, "target": [10000.0, 0.0], "in_group_a_range": 2.8, "out_group_r_strength": 68.0, "attractor_count": 49, "in_group_r_strength": 40.0, "in_group_a_strength": 20.0, "position": [56.80971124206686, 1.1290898645383813], "group_id": 1.0}, {"out_group_a_strength": 11.764705882352942, "friend_zone": [12, 13, 1, 2, 7, 10, 11, 5, 3, 14, 20, 25, 28, 31, 32, 33, 34, 35, 36, 37, 42, 43, 44, 45, 46, 47, 50, 51, 53, 54, 57, 58, 59, 63, 64, 65, 67, 68, 71, 73, 74, 75, 76, 77, 78, 81, 83, 85, 87, 90, 91, 94, 95, 97, 99], "out_group_r_range": 2.0, "target_a_strength": 22000000000.0, "radius": 0.3, "out_group_a_range": 2.8, "pedestrian_id": 15, "target_a_range": 435.0, "in_group_r_range": 2.0, "target": [10000.0, 0.0], "in_group_a_range": 2.8, "out_group_r_strength": 68.0, "attractor_count": 55, "in_group_r_strength": 40.0, "in_group_a_strength": 20.0, "position": [12.792613221057161, 4.5940606560026165], "group_id": 1.0}, {"out_group_a_strength": 11.764705882352942, "friend_zone": [0, 18, 6, 15, 19, 13, 3, 17, 12, 4, 20, 21, 23, 24, 25, 32, 35, 36, 38, 39, 43, 46, 47, 48, 49, 50, 51, 56, 58, 60, 61, 63, 65, 69, 70, 74, 75, 77, 79, 80, 81, 83, 84, 85, 90, 92, 94, 97], "out_group_r_range": 2.0, "target_a_strength": 22000000000.0, "radius": 0.3, "out_group_a_range": 2.8, "pedestrian_id": 16, "target_a_range": 435.0, "in_group_r_range": 2.0, "target": [10000.0, 0.0], "in_group_a_range": 2.8, "out_group_r_strength": 68.0, "attractor_count": 48, "in_group_r_strength": 40.0, "in_group_a_strength": 20.0, "position": [68.18304864013612, 4.145258040316205], "group_id": 1.0}, {"out_group_a_strength": 11.764705882352942, "friend_zone": [14, 9, 12, 7, 13, 3, 10, 19, 4, 8, 21, 22, 23, 24, 26, 27, 28, 29, 30, 32, 33, 34, 35, 36, 38, 39, 40, 41, 43, 47, 48, 51, 53, 55, 56, 57, 58, 62, 63, 64, 65, 67, 72, 74, 76, 77, 78, 79, 80, 82, 83, 85, 86, 87, 89, 90, 91, 92, 93, 95, 96, 97], "out_group_r_range": 2.0, "target_a_strength": 22000000000.0, "radius": 0.3, "out_group_a_range": 2.8, "pedestrian_id": 17, "target_a_range": 435.0, "in_group_r_range": 2.0, "target": [10000.0, 0.0], "in_group_a_range": 2.8, "out_group_r_strength": 68.0, "attractor_count": 62, "in_group_r_strength": 40.0, "in_group_a_strength": 20.0, "position": [93.53963578886743, 0.16757092064414708], "group_id": 1.0}, {"out_group_a_strength": 11.764705882352942, "friend_zone": [9, 12, 6, 1, 4, 7, 11, 14, 3, 8, 20, 22, 23, 24, 25, 31, 34, 36, 37, 38, 39, 40, 43, 44, 46, 47, 49, 50, 52, 54, 55, 57, 58, 59, 63, 64, 69, 70, 71, 72, 74, 75, 76, 77, 79, 80, 82, 83, 84, 85, 88, 95, 96, 98], "out_group_r_range": 2.0, "target_a_strength": 22000000000.0, "radius": 0.3, "out_group_a_range": 2.8, "pedestrian_id": 18, "target_a_range": 435.0, "in_group_r_range": 2.0, "target": [10000.0, 0.0], "in_group_a_range": 2.8, "out_group_r_strength": 68.0, "attractor_count": 54, "in_group_r_strength": 40.0, "in_group_a_strength": 20.0, "position": [80.95294171416286, 2.029513479314863], "group_id": 1.0}, {"out_group_a_strength": 11.764705882352942, "friend_zone": [8, 11, 1, 0, 18, 4, 17, 10, 2, 3, 20, 21, 23, 24, 25, 26, 33, 35, 38, 41, 44, 47, 48, 49, 50, 51, 56, 57, 59, 64, 65, 66, 68, 71, 73, 74, 75, 78, 79, 80, 83, 84, 86, 88, 89, 90, 92, 98], "out_group_r_range": 2.0, "target_a_strength": 22000000000.0, "radius": 0.3, "out_group_a_range": 2.8, "pedestrian_id": 19, "target_a_range": 435.0, "in_group_r_range": 2.0, "target": [10000.0, 0.0], "in_group_a_range": 2.8, "out_group_r_strength": 68.0, "attractor_count": 48, "in_group_r_strength": 40.0, "in_group_a_strength": 20.0, "position": [59.79924104228848, -6.7246177471812], "group_id": 1.0}, {"out_group_a_strength": 11.764705882352942, "friend_zone": [9, 16, 10, 7, 18, 6, 8, 4, 15, 19, 25, 26, 27, 28, 30, 31, 32, 33, 37, 38, 39, 42, 43, 46, 49, 52, 54, 55, 56, 58, 60, 61, 62, 66, 67, 68, 71, 73, 74, 76, 78, 80, 82, 87, 97, 99], "out_group_r_range": 2.0, "target_a_strength": 22000000000.0, "radius": 0.3, "out_group_a_range": 2.8, "pedestrian_id": 22, "target_a_range": 435.0, "in_group_r_range": 2.0, "target": [10000.0, 0.0], "in_group_a_range": 2.8, "out_group_r_strength": 68.0, "attractor_count": 46, "in_group_r_strength": 40.0, "in_group_a_strength": 20.0, "position": [49.51097213156228, 1.756624133625325], "group_id": 1.0}, {"out_group_a_strength": 11.764705882352942, "friend_zone": [16, 9, 6, 0, 1, 14, 10, 18, 13, 12, 24, 25, 27, 31, 32, 33, 35, 39, 41, 42, 43, 46, 50, 52, 53, 55, 58, 60, 61, 62, 64, 65, 67, 69, 70, 71, 72, 74, 75, 76, 77, 78, 79, 80, 82, 83, 84, 85, 86, 88, 89, 90, 92, 93, 94, 95, 97, 98, 99], "out_group_r_range": 2.0, "target_a_strength": 22000000000.0, "radius": 0.3, "out_group_a_range": 2.8, "pedestrian_id": 23, "target_a_range": 435.0, "in_group_r_range": 2.0, "target": [10000.0, 0.0], "in_group_a_range": 2.8, "out_group_r_strength": 68.0, "attractor_count": 59, "in_group_r_strength": 40.0, "in_group_a_strength": 20.0, "position": [65.00905385263601, 2.0472846558403597], "group_id": 1.0}, {"out_group_a_strength": 11.764705882352942, "friend_zone": [21, 16, 15, 18, 7, 6, 0, 22, 8, 12, 13, 4, 28, 29, 30, 31, 32, 34, 35, 36, 40, 42, 45, 46, 48, 49, 53, 56, 58, 59, 60, 61, 62, 65, 66, 67, 68, 69, 71, 72, 73, 75, 76, 79, 81, 84, 86, 87, 90, 91, 92, 94, 95, 98], "out_group_r_range": 2.0, "target_a_strength": 22000000000.0, "radius": 0.3, "out_group_a_range": 2.8, "pedestrian_id": 26, "target_a_range": 435.0, "in_group_r_range": 2.0, "target": [10000.0, 0.0], "in_group_a_range": 2.8, "out_group_r_strength": 68.0, "attractor_count": 54, "in_group_r_strength": 40.0, "in_group_a_strength": 20.0, "position": [67.32617057808089, -3.33032908247202], "group_id": 1.0}, {"out_group_a_strength": 11.764705882352942, "friend_zone": [19, 8, 2, 3, 6, 7, 10, 17, 11, 18, 16, 13, 28, 30, 32, 34, 37, 41, 42, 44, 47, 49, 50, 52, 54, 55, 56, 59, 62, 64, 65, 66, 67, 68, 71, 77, 78, 79, 80, 81, 83, 85, 86, 91, 95, 96, 98, 99], "out_group_r_range": 2.0, "target_a_strength": 22000000000.0, "radius": 0.3, "out_group_a_range": 2.8, "pedestrian_id": 27, "target_a_range": 435.0, "in_group_r_range": 2.0, "target": [10000.0, 0.0], "in_group_a_range": 2.8, "out_group_r_strength": 68.0, "attractor_count": 48, "in_group_r_strength": 40.0, "in_group_a_strength": 20.0, "position": [23.53252306711946, 7.92732679099143], "group_id": 1.0}, {"out_group_a_strength": 11.764705882352942, "friend_zone": [0, 15, 17, 14, 4, 10, 23, 21, 19, 12, 25, 2, 18, 6, 33, 35, 36, 40, 43, 45, 46, 49, 50, 51, 52, 55, 56, 61, 63, 66, 77, 81, 84, 85, 86, 87, 94, 95, 96, 99], "out_group_r_range": 2.0, "target_a_strength": 22000000000.0, "radius": 0.3, "out_group_a_range": 2.8, "pedestrian_id": 30, "target_a_range": 435.0, "in_group_r_range": 2.0, "target": [10000.0, 0.0], "in_group_a_range": 2.8, "out_group_r_strength": 68.0, "attractor_count": 40, "in_group_r_strength": 40.0, "in_group_a_strength": 20.0, "position": [56.220753634766325, -3.5923440333509435], "group_id": 1.0}, {"out_group_a_strength": 11.764705882352942, "friend_zone": [8, 19, 22, 9, 12, 24, 11, 15, 1, 16, 27, 23, 10, 17, 32, 34, 35, 39, 40, 41, 42, 43, 44, 45, 48, 51, 52, 53, 54, 59, 60, 62, 64, 67, 69, 70, 72, 73, 74, 75, 76, 77, 79, 82, 90, 91, 92, 93, 97], "out_group_r_range": 2.0, "target_a_strength": 22000000000.0, "radius": 0.3, "out_group_a_range": 2.8, "pedestrian_id": 31, "target_a_range": 435.0, "in_group_r_range": 2.0, "target": [10000.0, 0.0], "in_group_a_range": 2.8, "out_group_r_strength": 68.0, "attractor_count": 49, "in_group_r_strength": 40.0, "in_group_a_strength": 20.0, "position": [88.44358143764015, -0.25346503788269575], "group_id": 1.0}, {"out_group_a_strength": 11.764705882352942, "friend_zone": [19, 30, 25, 18, 5, 4, 21, 1, 13, 31, 8, 7, 17, 23, 22, 11, 36, 37, 39, 40, 41, 46, 48, 49, 50, 51, 54, 55, 57, 58, 59, 60, 61, 62, 66, 68, 69, 73, 74, 80, 83, 84, 85, 87, 94, 95, 96, 98, 99], "out_group_r_range": 2.0, "target_a_strength": 22000000000.0, "radius": 0.3, "out_group_a_range": 2.8, "pedestrian_id": 34, "target_a_range": 435.0, "in_group_r_range": 2.0, "target": [10000.0, 0.0], "in_group_a_range": 2.8, "out_group_r_strength": 68.0, "attractor_count": 49, "in_group_r_strength": 40.0, "in_group_a_strength": 20.0, "position": [37.946559023432705, 7.3675950803635315], "group_id": 1.0}, {"out_group_a_strength": 11.764705882352942, "friend_zone": [23, 3, 2, 4, 5, 15, 9, 19, 31, 11, 6, 21, 27, 30, 13, 12, 39, 40, 42, 51, 52, 55, 59, 64, 66, 67, 68, 69, 70, 71, 74, 77, 79, 80, 81, 86, 87, 91, 92, 94, 98], "out_group_r_range": 2.0, "target_a_strength": 22000000000.0, "radius": 0.3, "out_group_a_range": 2.8, "pedestrian_id": 35, "target_a_range": 435.0, "in_group_r_range": 2.0, "target": [10000.0, 0.0], "in_group_a_range": 2.8, "out_group_r_strength": 68.0, "attractor_count": 41, "in_group_r_strength": 40.0, "in_group_a_strength": 20.0, "position": [-6.867571132165987, -3.1274924241317335], "group_id": 1.0}, {"out_group_a_strength": 11.764705882352942, "friend_zone": [7, 35, 29, 33, 10, 9, 11, 2, 34, 25, 30, 23, 17, 20, 13, 22, 0, 6, 49, 50, 53, 54, 55, 56, 60, 64, 65, 72, 76, 77, 78, 84, 85, 86, 88, 89, 90, 91, 92, 93, 94, 95, 98, 99], "out_group_r_range": 2.0, "target_a_strength": 22000000000.0, "radius": 0.3, "out_group_a_range": 2.8, "pedestrian_id": 38, "target_a_range": 435.0, "in_group_r_range": 2.0, "target": [10000.0, 0.0], "in_group_a_range": 2.8, "out_group_r_strength": 68.0, "attractor_count": 44, "in_group_r_strength": 40.0, "in_group_a_strength": 20.0, "position": [53.27084600536974, 4.96096157464973], "group_id": 1.0}, {"out_group_a_strength": 11.764705882352942, "friend_zone": [15, 2, 18, 22, 29, 8, 20, 5, 14, 30, 4, 28, 3, 19, 26, 12, 16, 32, 41, 49, 57, 58, 63, 69, 70, 74, 75, 79, 81, 85, 87, 89, 90, 91, 93, 95, 97, 99], "out_group_r_range": 2.0, "target_a_strength": 22000000000.0, "radius": 0.3, "out_group_a_range": 2.8, "pedestrian_id": 39, "target_a_range": 435.0, "in_group_r_range": 2.0, "target": [10000.0, 0.0], "in_group_a_range": 2.8, "out_group_r_strength": 68.0, "attractor_count": 38, "in_group_r_strength": 40.0, "in_group_a_strength": 20.0, "position": [46.604347974658474, 6.055600785832223], "group_id": 1.0}, {"out_group_a_strength": 11.764705882352942, "friend_zone": [2, 22, 29, 24, 17, 35, 36, 12, 31, 15, 32, 16, 11, 37, 13, 4, 6, 21, 27, 1, 45, 48, 52, 55, 56, 57, 58, 60, 61, 63, 65, 68, 73, 75, 78, 79, 81, 82, 83, 84, 85, 86, 87, 88, 89, 90, 91, 92, 98], "out_group_r_range": 2.0, "target_a_strength": 22000000000.0, "radius": 0.3, "out_group_a_range": 2.8, "pedestrian_id": 42, "target_a_range": 435.0, "in_group_r_range": 2.0, "target": [10000.0, 0.0], "in_group_a_range": 2.8, "out_group_r_strength": 68.0, "attractor_count": 49, "in_group_r_strength": 40.0, "in_group_a_strength": 20.0, "position": [33.40148161588136, 2.424973225012663], "group_id": 1.0}, {"out_group_a_strength": 11.764705882352942, "friend_zone": [29, 39, 21, 5, 0, 25, 6, 26, 31, 22, 3, 11, 9, 7, 19, 4, 2, 12, 32, 28, 46, 48, 49, 51, 52, 56, 57, 58, 61, 62, 64, 65, 67, 68, 69, 72, 75, 76, 78, 79, 81, 82, 83, 90, 91, 92, 96, 98], "out_group_r_range": 2.0, "target_a_strength": 22000000000.0, "radius": 0.3, "out_group_a_range": 2.8, "pedestrian_id": 43, "target_a_range": 435.0, "in_group_r_range": 2.0, "target": [10000.0, 0.0], "in_group_a_range": 2.8, "out_group_r_strength": 68.0, "attractor_count": 48, "in_group_r_strength": 40.0, "in_group_a_strength": 20.0, "position": [37.665685844814064, -8.244080287669187], "group_id": 1.0}, {"out_group_a_strength": 11.764705882352942, "friend_zone": [41, 23, 33, 11, 42, 4, 26, 9, 7, 27, 14, 15, 0, 8, 38, 43, 19, 12, 17, 40, 3, 24, 49, 50, 52, 54, 55, 56, 57, 58, 59, 61, 62, 66, 67, 68, 69, 70, 71, 72, 73, 75, 78, 79, 81, 82, 86, 90, 93], "out_group_r_range": 2.0, "target_a_strength": 22000000000.0, "radius": 0.3, "out_group_a_range": 2.8, "pedestrian_id": 46, "target_a_range": 435.0, "in_group_r_range": 2.0, "target": [10000.0, 0.0], "in_group_a_range": 2.8, "out_group_r_strength": 68.0, "attractor_count": 49, "in_group_r_strength": 40.0, "in_group_a_strength": 20.0, "position": [4.333841632377436, 1.3142744302084335], "group_id": 1.0}, {"out_group_a_strength": 11.764705882352942, "friend_zone": [9, 4, 2, 3, 17, 21, 32, 42, 28, 19, 13, 36, 37, 14, 31, 5, 16, 40, 41, 6, 18, 29, 49, 50, 52, 55, 61, 64, 65, 68, 70, 71, 72, 78, 79, 80, 81, 82, 86, 88, 91, 92, 94, 97, 98, 99], "out_group_r_range": 2.0, "target_a_strength": 22000000000.0, "radius": 0.3, "out_group_a_range": 2.8, "pedestrian_id": 47, "target_a_range": 435.0, "in_group_r_range": 2.0, "target": [10000.0, 0.0], "in_group_a_range": 2.8, "out_group_r_strength": 68.0, "attractor_count": 46, "in_group_r_strength": 40.0, "in_group_a_strength": 20.0, "position": [-2.4895533166275623, -8.082249715884279], "group_id": 1.0}, {"out_group_a_strength": 11.764705882352942, "friend_zone": [6, 35, 16, 29, 23, 36, 22, 20, 19, 24, 32, 27, 5, 21, 3, 28, 47, 44, 34, 12, 10, 9, 46, 2, 52, 53, 56, 60, 61, 62, 63, 65, 69, 70, 71, 73, 75, 77, 78, 81, 82, 83, 84, 85, 86, 87, 89, 95, 99], "out_group_r_range": 2.0, "target_a_strength": 22000000000.0, "radius": 0.3, "out_group_a_range": 2.8, "pedestrian_id": 50, "target_a_range": 435.0, "in_group_r_range": 2.0, "target": [10000.0, 0.0], "in_group_a_range": 2.8, "out_group_r_strength": 68.0, "attractor_count": 49, "in_group_r_strength": 40.0, "in_group_a_strength": 20.0, "position": [4.638075833614651, -8.822397592450555], "group_id": 1.0}, {"out_group_a_strength": 11.764705882352942, "friend_zone": [40, 29, 41, 18, 21, 42, 23, 14, 34, 28, 27, 30, 47, 39, 32, 3, 44, 38, 24, 6, 35, 25, 19, 12, 56, 58, 59, 62, 63, 64, 65, 68, 71, 73, 76, 77, 78, 79, 80, 82, 83, 84, 85, 86, 87, 88, 89, 90, 91, 92, 93, 94, 99], "out_group_r_range": 2.0, "target_a_strength": 22000000000.0, "radius": 0.3, "out_group_a_range": 2.8, "pedestrian_id": 51, "target_a_range": 435.0, "in_group_r_range": 2.0, "target": [10000.0, 0.0], "in_group_a_range": 2.8, "out_group_r_strength": 68.0, "attractor_count": 53, "in_group_r_strength": 40.0, "in_group_a_strength": 20.0, "position": [-4.650853812897855, 7.96492009551065], "group_id": 1.0}, {"out_group_a_strength": 11.764705882352942, "friend_zone": [49, 10, 13, 14, 30, 47, 28, 18, 3, 22, 21, 5, 42, 29, 26, 45, 43, 33, 20, 37, 39, 11, 31, 8, 23, 0, 56, 57, 58, 59, 60, 63, 64, 67, 68, 69, 72, 73, 74, 75, 76, 77, 78, 79, 80, 81, 82, 83, 85, 88, 89, 95, 96, 98], "out_group_r_range": 2.0, "target_a_strength": 22000000000.0, "radius": 0.3, "out_group_a_range": 2.8, "pedestrian_id": 54, "target_a_range": 435.0, "in_group_r_range": 2.0, "target": [10000.0, 0.0], "in_group_a_range": 2.8, "out_group_r_strength": 68.0, "attractor_count": 54, "in_group_r_strength": 40.0, "in_group_a_strength": 20.0, "position": [-1.0829151923614195, -2.4232725540472098], "group_id": 1.0}, {"out_group_a_strength": 11.764705882352942, "friend_zone": [28, 38, 48, 14, 41, 51, 47, 46, 2, 17, 37, 19, 27, 18, 4, 8, 43, 12, 24, 15, 35, 9, 32, 20, 7, 31, 60, 63, 66, 68, 69, 70, 71, 73, 78, 79, 81, 83, 84, 88, 91, 93, 94, 95, 98, 99], "out_group_r_range": 2.0, "target_a_strength": 22000000000.0, "radius": 0.3, "out_group_a_range": 2.8, "pedestrian_id": 55, "target_a_range": 435.0, "in_group_r_range": 2.0, "target": [10000.0, 0.0], "in_group_a_range": 2.8, "out_group_r_strength": 68.0, "attractor_count": 46, "in_group_r_strength": 40.0, "in_group_a_strength": 20.0, "position": [-9.953625217128678, -4.513052771463456], "group_id": 1.0}, {"out_group_a_strength": 11.764705882352942, "friend_zone": [29, 10, 0, 50, 28, 19, 6, 16, 46, 32, 33, 20, 42, 54, 47, 15, 52, 26, 9, 37, 23, 39, 27, 43, 45, 48, 31, 4, 60, 64, 65, 67, 72, 75, 76, 77, 78, 80, 83, 85, 86, 90, 93, 94, 98, 99], "out_group_r_range": 2.0, "target_a_strength": 22000000000.0, "radius": 0.3, "out_group_a_range": 2.8, "pedestrian_id": 58, "target_a_range": 435.0, "in_group_r_range": 2.0, "target": [10000.0, 0.0], "in_group_a_range": 2.8, "out_group_r_strength": 68.0, "attractor_count": 46, "in_group_r_strength": 40.0, "in_group_a_strength": 20.0, "position": [9.263063003530073, 1.4176652682117716], "group_id": 1.0}, {"out_group_a_strength": 11.764705882352942, "friend_zone": [16, 7, 8, 36, 44, 34, 41, 30, 53, 12, 35, 0, 21, 1, 13, 47, 28, 38, 40, 37, 52, 32, 6, 22, 15, 10, 25, 11, 63, 64, 65, 69, 70, 71, 78, 79, 84, 85, 88, 90, 91, 92, 94, 95, 96, 99], "out_group_r_range": 2.0, "target_a_strength": 22000000000.0, "radius": 0.3, "out_group_a_range": 2.8, "pedestrian_id": 59, "target_a_range": 435.0, "in_group_r_range": 2.0, "target": [10000.0, 0.0], "in_group_a_range": 2.8, "out_group_r_strength": 68.0, "attractor_count": 46, "in_group_r_strength": 40.0, "in_group_a_strength": 20.0, "position": [-40.2868852398619, 0.5111478673218863], "group_id": 1.0}, {"out_group_a_strength": 11.764705882352942, "friend_zone": [18, 34, 6, 40, 14, 44, 8, 55, 49, 41, 59, 22, 5, 29, 24, 35, 20, 54, 15, 7, 38, 52, 19, 26, 23, 27, 45, 36, 25, 21, 67, 71, 74, 75, 77, 79, 80, 92, 93, 94, 97, 98, 99], "out_group_r_range": 2.0, "target_a_strength": 22000000000.0, "radius": 0.3, "out_group_a_range": 2.8, "pedestrian_id": 62, "target_a_range": 435.0, "in_group_r_range": 2.0, "target": [10000.0, 0.0], "in_group_a_range": 2.8, "out_group_r_strength": 68.0, "attractor_count": 43, "in_group_r_strength": 40.0, "in_group_a_strength": 20.0, "position": [-1.4741796755605079, 3.0053576069530283], "group_id": 1.0}, {"out_group_a_strength": 11.764705882352942, "friend_zone": [9, 53, 24, 14, 27, 25, 51, 52, 4, 6, 47, 35, 31, 37, 55, 15, 23, 44, 29, 8, 33, 30, 54, 45, 21, 43, 36, 20, 16, 1, 66, 67, 69, 71, 74, 75, 76, 77, 78, 81, 87, 88, 89, 94, 99], "out_group_r_range": 2.0, "target_a_strength": 22000000000.0, "radius": 0.3, "out_group_a_range": 2.8, "pedestrian_id": 63, "target_a_range": 435.0, "in_group_r_range": 2.0, "target": [10000.0, 0.0], "in_group_a_range": 2.8, "out_group_r_strength": 68.0, "attractor_count": 45, "in_group_r_strength": 40.0, "in_group_a_strength": 20.0, "position": [-22.745357745616676, 8.712134636527795], "group_id": 1.0}, {"out_group_a_strength": 11.764705882352942, "friend_zone": [41, 8, 42, 9, 48, 40, 4, 31, 16, 22, 47, 15, 1, 58, 10, 14, 44, 55, 61, 12, 29, 59, 5, 18, 63, 11, 51, 35, 52, 38, 0, 46, 68, 69, 70, 72, 73, 74, 76, 77, 78, 80, 81, 82, 84, 85, 87, 88, 89, 90, 91, 93, 95, 96, 97, 99], "out_group_r_range": 2.0, "target_a_strength": 22000000000.0, "radius": 0.3, "out_group_a_range": 2.8, "pedestrian_id": 66, "target_a_range": 435.0, "in_group_r_range": 2.0, "target": [10000.0, 0.0], "in_group_a_range": 2.8, "out_group_r_strength": 68.0, "attractor_count": 56, "in_group_r_strength": 40.0, "in_group_a_strength": 20.0, "position": [24.590085365415153, -6.620110955918116], "group_id": 1.0}, {"out_group_a_strength": 11.764705882352942, "friend_zone": [4, 58, 27, 12, 25, 59, 2, 18, 20, 23, 29, 40, 51, 16, 26, 6, 15, 32, 11, 60, 62, 55, 44, 17, 48, 24, 14, 50, 56, 43, 8, 61, 69, 70, 71, 73, 75, 76, 77, 78, 81, 86, 87, 88, 89, 91, 92, 93, 95, 96], "out_group_r_range": 2.0, "target_a_strength": 22000000000.0, "radius": 0.3, "out_group_a_range": 2.8, "pedestrian_id": 67, "target_a_range": 435.0, "in_group_r_range": 2.0, "target": [10000.0, 0.0], "in_group_a_range": 2.8, "out_group_r_strength": 68.0, "attractor_count": 50, "in_group_r_strength": 40.0, "in_group_a_strength": 20.0, "position": [0.9432726040972946, 7.089965175713281], "group_id": 1.0}, {"out_group_a_strength": 11.764705882352942, "friend_zone": [31, 0, 24, 1, 8, 32, 36, 26, 7, 3, 45, 4, 23, 14, 49, 63, 59, 57, 34, 11, 56, 20, 30, 50, 66, 38, 21, 19, 41, 47, 12, 18, 37, 52, 72, 73, 74, 76, 78, 80, 81, 88, 89, 91, 93, 97, 98], "out_group_r_range": 2.0, "target_a_strength": 22000000000.0, "radius": 0.3, "out_group_a_range": 2.8, "pedestrian_id": 70, "target_a_range": 435.0, "in_group_r_range": 2.0, "target": [10000.0, 0.0], "in_group_a_range": 2.8, "out_group_r_strength": 68.0, "attractor_count": 47, "in_group_r_strength": 40.0, "in_group_a_strength": 20.0, "position": [-19.976035365465396, 1.7711538061718999], "group_id": 1.0}, {"out_group_a_strength": 11.764705882352942, "friend_zone": [45, 64, 48, 66, 7, 34, 38, 55, 26, 0, 62, 3, 65, 5, 33, 8, 21, 54, 35, 4, 31, 24, 10, 59, 29, 11, 14, 50, 18, 44, 47, 67, 13, 12, 74, 75, 76, 78, 79, 80, 82, 83, 85, 90, 93, 96, 97, 98], "out_group_r_range": 2.0, "target_a_strength": 22000000000.0, "radius": 0.3, "out_group_a_range": 2.8, "pedestrian_id": 71, "target_a_range": 435.0, "in_group_r_range": 2.0, "target": [10000.0, 0.0], "in_group_a_range": 2.8, "out_group_r_strength": 68.0, "attractor_count": 48, "in_group_r_strength": 40.0, "in_group_a_strength": 20.0, "position": [-7.517999276434918, -7.4533850285678485], "group_id": 1.0}, {"out_group_a_strength": 11.764705882352942, "friend_zone": [42, 15, 13, 57, 1, 62, 58, 46, 31, 17, 51, 38, 68, 41, 67, 61, 50, 9, 25, 18, 29, 22, 16, 52, 66, 44, 59, 21, 69, 28, 35, 30, 60, 20, 48, 12, 77, 79, 81, 84, 85, 87, 90, 91, 92, 94, 96, 97], "out_group_r_range": 2.0, "target_a_strength": 22000000000.0, "radius": 0.3, "out_group_a_range": 2.8, "pedestrian_id": 74, "target_a_range": 435.0, "in_group_r_range": 2.0, "target": [10000.0, 0.0], "in_group_a_range": 2.8, "out_group_r_strength": 68.0, "attractor_count": 48, "in_group_r_strength": 40.0, "in_group_a_strength": 20.0, "position": [-30.944720208403076, 7.7903986610465115], "group_id": 1.0}, {"out_group_a_strength": 11.764705882352942, "friend_zone": [43, 31, 55, 20, 1, 28, 44, 61, 36, 35, 17, 46, 38, 68, 25, 63, 27, 32, 4, 9, 11, 14, 3, 50, 12, 48, 30, 47, 5, 33, 24, 15, 22, 57, 59, 67, 76, 83, 86, 87, 88, 92, 93, 96, 99], "out_group_r_range": 2.0, "target_a_strength": 22000000000.0, "radius": 0.3, "out_group_a_range": 2.8, "pedestrian_id": 75, "target_a_range": 435.0, "in_group_r_range": 2.0, "target": [10000.0, 0.0], "in_group_a_range": 2.8, "out_group_r_strength": 68.0, "attractor_count": 45, "in_group_r_strength": 40.0, "in_group_a_strength": 20.0, "position": [-26.171680274643396, -6.095418365332399], "group_id": 1.0}, {"out_group_a_strength": 11.764705882352942, "friend_zone": [24, 49, 23, 22, 7, 13, 65, 42, 16, 4, 75, 21, 35, 62, 70, 32, 17, 60, 53, 6, 33, 48, 15, 2, 59, 40, 41, 0, 67, 74, 10, 18, 66, 36, 25, 26, 57, 45, 80, 84, 85, 86, 88, 92, 94, 96, 99], "out_group_r_range": 2.0, "target_a_strength": 22000000000.0, "radius": 0.3, "out_group_a_range": 2.8, "pedestrian_id": 78, "target_a_range": 435.0, "in_group_r_range": 2.0, "target": [10000.0, 0.0], "in_group_a_range": 2.8, "out_group_r_strength": 68.0, "attractor_count": 47, "in_group_r_strength": 40.0, "in_group_a_strength": 20.0, "position": [-35.73413054934964, 2.541128578929083], "group_id": 1.0}, {"out_group_a_strength": 11.764705882352942, "friend_zone": [11, 8, 57, 44, 35, 52, 53, 23, 15, 69, 6, 75, 10, 38, 17, 30, 49, 0, 26, 64, 50, 22, 19, 31, 43, 39, 14, 13, 62, 66, 61, 7, 47, 73, 71, 72, 40, 29, 80, 84, 85, 88, 89, 91, 92, 94, 95, 97, 98, 99], "out_group_r_range": 2.0, "target_a_strength": 22000000000.0, "radius": 0.3, "out_group_a_range": 2.8, "pedestrian_id": 79, "target_a_range": 435.0, "in_group_r_range": 2.0, "target": [10000.0, 0.0], "in_group_a_range": 2.8, "out_group_r_strength": 68.0, "attractor_count": 50, "in_group_r_strength": 40.0, "in_group_a_strength": 20.0, "position": [19.119851038167806, -3.6995899795406757], "group_id": 1.0}, {"out_group_a_strength": 11.764705882352942, "friend_zone": [57, 44, 19, 48, 67, 61, 39, 9, 51, 3, 5, 2, 66, 47, 21, 35, 34, 68, 38, 28, 26, 70, 8, 29, 65, 33, 42, 31, 7, 77, 69, 27, 46, 63, 49, 37, 50, 30, 76, 62, 84, 85, 86, 87, 89, 91, 92, 93, 96, 97, 98, 99], "out_group_r_range": 2.0, "target_a_strength": 22000000000.0, "radius": 0.3, "out_group_a_range": 2.8, "pedestrian_id": 82, "target_a_range": 435.0, "in_group_r_range": 2.0, "target": [10000.0, 0.0], "in_group_a_range": 2.8, "out_group_r_strength": 68.0, "attractor_count": 52, "in_group_r_strength": 40.0, "in_group_a_strength": 20.0, "position": [-45.91838445500011, -6.419751715471386], "group_id": 1.0}, {"out_group_a_strength": 11.764705882352942, "friend_zone": [9, 28, 48, 39, 66, 53, 59, 22, 78, 74, 21, 7, 49, 38, 65, 20, 58, 6, 3, 63, 69, 25, 15, 55, 33, 32, 35, 43, 62, 0, 72, 51, 24, 79, 46, 1, 70, 68, 71, 40, 85, 86, 88, 90, 92, 93, 94, 95, 98, 99], "out_group_r_range": 2.0, "target_a_strength": 22000000000.0, "radius": 0.3, "out_group_a_range": 2.8, "pedestrian_id": 83, "target_a_range": 435.0, "in_group_r_range": 2.0, "target": [10000.0, 0.0], "in_group_a_range": 2.8, "out_group_r_strength": 68.0, "attractor_count": 50, "in_group_r_strength": 40.0, "in_group_a_strength": 20.0, "position": [-13.94689116171185, -3.862679146311298], "group_id": 1.0}, {"out_group_a_strength": 11.764705882352942, "friend_zone": [42, 58, 69, 81, 37, 46, 3, 17, 8, 12, 47, 83, 10, 82, 30, 25, 45, 11, 26, 21, 27, 13, 41, 28, 23, 78, 39, 7, 2, 4, 64, 53, 70, 15, 51, 29, 48, 73, 16, 79, 67, 9, 88, 89, 90, 92, 96, 97], "out_group_r_range": 2.0, "target_a_strength": 22000000000.0, "radius": 0.3, "out_group_a_range": 2.8, "pedestrian_id": 86, "target_a_range": 435.0, "in_group_r_range": 2.0, "target": [10000.0, 0.0], "in_group_a_range": 2.8, "out_group_r_strength": 68.0, "attractor_count": 48, "in_group_r_strength": 40.0, "in_group_a_strength": 20.0, "position": [-7.572086523847323, 8.583156688619514], "group_id": 1.0}, {"out_group_a_strength": 11.764705882352942, "friend_zone": [59, 63, 10, 25, 29, 73, 1, 39, 78, 42, 28, 11, 67, 80, 22, 77, 58, 48, 0, 6, 43, 72, 12, 32, 65, 21, 20, 36, 55, 69, 56, 37, 68, 53, 15, 62, 27, 19, 44, 35, 70, 16, 88, 89, 90, 91, 98, 99], "out_group_r_range": 2.0, "target_a_strength": 22000000000.0, "radius": 0.3, "out_group_a_range": 2.8, "pedestrian_id": 87, "target_a_range": 435.0, "in_group_r_range": 2.0, "target": [10000.0, 0.0], "in_group_a_range": 2.8, "out_group_r_strength": 68.0, "attractor_count": 48, "in_group_r_strength": 40.0, "in_group_a_strength": 20.0, "position": [-31.227430511183737, -0.2784395065709805], "group_id": 1.0}, {"out_group_a_strength": 11.764705882352942, "friend_zone": [40, 73, 63, 5, 11, 38, 44, 15, 45, 71, 9, 12, 4, 53, 0, 55, 41, 58, 50, 87, 59, 62, 1, 3, 10, 86, 19, 75, 51, 28, 74, 39, 60, 78, 82, 32, 24, 46, 64, 6, 68, 54, 66, 8, 92, 94, 95, 99], "out_group_r_range": 2.0, "target_a_strength": 22000000000.0, "radius": 0.3, "out_group_a_range": 2.8, "pedestrian_id": 90, "target_a_range": 435.0, "in_group_r_range": 2.0, "target": [10000.0, 0.0], "in_group_a_range": 2.8, "out_group_r_strength": 68.0, "attractor_count": 48, "in_group_r_strength": 40.0, "in_group_a_strength": 20.0, "position": [-28.902981917436005, 4.4275249288545595], "group_id": 1.0}, {"out_group_a_strength": 11.764705882352942, "friend_zone": [4, 35, 42, 2, 43, 70, 38, 71, 62, 75, 39, 25, 9, 45, 85, 65, 60, 80, 83, 81, 54, 19, 1, 53, 64, 24, 16, 23, 15, 78, 68, 22, 61, 34, 21, 55, 11, 33, 76, 44, 49, 14, 56, 32, 92, 93, 97], "out_group_r_range": 2.0, "target_a_strength": 22000000000.0, "radius": 0.3, "out_group_a_range": 2.8, "pedestrian_id": 91, "target_a_range": 435.0, "in_group_r_range": 2.0, "target": [10000.0, 0.0], "in_group_a_range": 2.8, "out_group_r_strength": 68.0, "attractor_count": 47, "in_group_r_strength": 40.0, "in_group_a_strength": 20.0, "position": [-44.55607215175636, -0.6934387062675552], "group_id": 1.0}, {"out_group_a_strength": 11.764705882352942, "friend_zone": [37, 69, 12, 78, 20, 1, 68, 79, 39, 88, 23, 41, 0, 90, 86, 31, 16, 85, 30, 7, 72, 27, 48, 40, 25, 65, 83, 50, 58, 66, 91, 73, 3, 29, 63, 46, 81, 24, 84, 18, 71, 28, 17, 80, 67, 6, 96, 97, 99], "out_group_r_range": 2.0, "target_a_strength": 22000000000.0, "radius": 0.3, "out_group_a_range": 2.8, "pedestrian_id": 94, "target_a_range": 435.0, "in_group_r_range": 2.0, "target": [10000.0, 0.0], "in_group_a_range": 2.8, "out_group_r_strength": 68.0, "attractor_count": 49, "in_group_r_strength": 40.0, "in_group_a_strength": 20.0, "position": [-46.187376820635464, 5.182267191293474], "group_id": 1.0}, {"out_group_a_strength": 11.764705882352942, "friend_zone": [5, 26, 27, 6, 79, 51, 3, 16, 44, 43, 62, 15, 14, 87, 68, 64, 55, 21, 70, 59, 67, 65, 76, 48, 35, 33, 60, 85, 47, 71, 38, 24, 82, 22, 34, 45, 63, 73, 37, 74, 28, 25, 41, 20, 90, 2, 97, 99], "out_group_r_range": 2.0, "target_a_strength": 22000000000.0, "radius": 0.3, "out_group_a_range": 2.8, "pedestrian_id": 95, "target_a_range": 435.0, "in_group_r_range": 2.0, "target": [10000.0, 0.0], "in_group_a_range": 2.8, "out_group_r_strength": 68.0, "attractor_count": 48, "in_group_r_strength": 40.0, "in_group_a_strength": 20.0, "position": [-25.295414724216283, 2.311481649833869], "group_id": 1.0}, {"out_group_a_strength": 11.764705882352942, "friend_zone": [33, 25, 64, 0, 86, 75, 93, 79, 53, 56, 62, 10, 59, 31, 1, 2, 80, 27, 95, 42, 47, 41, 16, 58, 87, 66, 81, 85, 69, 84, 49, 37, 18, 34, 8, 89, 67, 35, 20, 12, 88, 38, 94, 17, 82, 13, 44, 52], "out_group_r_range": 2.0, "target_a_strength": 22000000000.0, "radius": 0.3, "out_group_a_range": 2.8, "pedestrian_id": 98, "target_a_range": 435.0, "in_group_r_range": 2.0, "target": [10000.0, 0.0], "in_group_a_range": 2.8, "out_group_r_strength": 68.0, "attractor_count": 48, "in_group_r_strength": 40.0, "in_group_a_strength": 20.0, "position": [-44.35046335129705, -9.482349635837616], "group_id": 1.0}, {"out_group_a_strength": 11.764705882352942, "friend_zone": [86, 25, 0, 10, 52, 44, 6, 76, 69, 38, 70, 37, 93, 22, 83, 30, 77, 34, 62, 89, 58, 23, 92, 80, 66, 56, 2, 18, 11, 42, 51, 73, 84, 72, 36, 5, 63, 33, 24, 74, 7, 28, 26, 59, 13, 57, 85, 81], "out_group_r_range": 2.0, "target_a_strength": 22000000000.0, "radius": 0.3, "out_group_a_range": 2.8, "pedestrian_id": 99, "target_a_range": 435.0, "in_group_r_range": 2.0, "target": [10000.0, 0.0], "in_group_a_range": 2.8, "out_group_r_strength": 68.0, "attractor_count": 48, "in_group_r_strength": 40.0, "in_group_a_strength": 20.0, "position": [-48.469167997618975, 9.239969749243528], "group_id": 1.0}]}